revKimi/__init__.py
revKimi/config.py
revKimi/exceptions.py
revKimi/main.py
revkimi-0.0.3.dist-info/METADATA
revkimi-0.0.3.dist-info/WHEEL
revkimi-0.0.3.dist-info/licenses/LICENSE
revkimi-0.0.3.dist-info/RECORD
