Metadata-Version: 2.3
Name: revKimi
Version: 0.0.3
Summary: kimi逆向api
Project-URL: Homepage, https://github.com/old-dream321/revKimi
Author-email: old-dream321 <hzz123123@outlook.com>
License: MIT License
License-File: LICENSE
Classifier: License :: OSI Approved :: MIT License
Classifier: Operating System :: OS Independent
Classifier: Programming Language :: Python :: 3
Requires-Python: >=3.9
Requires-Dist: filetype
Requires-Dist: requests
